rdkit2ase/__init__.py
rdkit2ase/ase2x.py
rdkit2ase/bond_order.py
rdkit2ase/com.py
rdkit2ase/compress.py
rdkit2ase/networkx2x.py
rdkit2ase/pack.py
rdkit2ase/rdkit2x.py
rdkit2ase/smiles2x.py
rdkit2ase/substructure.py
rdkit2ase/utils.py
rdkit2ase-0.1.13.dist-info/METADATA
rdkit2ase-0.1.13.dist-info/WHEEL
rdkit2ase-0.1.13.dist-info/licenses/LICENSE
rdkit2ase-0.1.13.dist-info/RECORD
